{
  "소년이 온다": [
    {
      "location": "대한민국 광주광역시",
      "event": "1980년 5.18 민주화운동 당시 벌어진 비극적인 학살을 중심으로 한다. 주요 배경은 전남도청이다."
    }
  ],
  "작별하지 않는다": [
    {
      "location": "제주도",
      "event": "제주 4.3 사건은 이 소설의 핵심 배경이다. 주인공은 당시의 아픔을 간직한 채 진실을 찾아간다."
    }
  ],
  "태백산맥": [
    {
      "location": "전라남도 여수, 순천, 벌교",
      "event": "1948년 여순사건과 빨치산 운동 등 해방 이후 이념 갈등을 다룸"
    }
  ],
  "토지": [
    {
      "location": "경상남도 하동 평사리",
      "event": "한말부터 일제강점기까지 한국 민족의 삶과 피폐를 그린 대서사시"
    }
  ],
  "동백꽃 필 무렵": [
    {
      "location": "포항 구룡포",
      "event": "구룡포를 배경으로 촬영된 드라마로, 등장인물의 일상과 사건들이 이 지역에서 펼쳐진다."
    }
  ],
  "순이삼촌": [
    {
      "location": "제주도",
      "event": "1948년 제주 4.3 사건 당시 여성과 민간인의 피해를 다룸"
    }
  ],
  "자전거 도둑": [
    {
      "location": "대한민국 서울특별시",
      "event": "서울 변두리 서민가를 배경으로 도시 빈민층의 생활과 가족 이야기를 다룸.",
      "note": "정확한 동네 스펙은 작품·판본에 따라 다르게 해석됨."
    }
  ],
  "칼의 노래": [
    {
      "location": "대한민국 전라남도 해남",
      "event": "임진왜란 당시 이순신 장군의 시선으로 해전과 인간 내면을 그린 역사소설."
    }
  ],
  "난장이가 쏘아올린 작은 공": [
    {
      "location": "대한민국 서울 변두리 공단 지역",
      "event": "1970년대 산업화 과정에서 도시 빈민과 노동자의 삶을 묘사."
    }
  ],
  "82년생 김지영": [
    {
      "location": "서울",
      "event": "1980년대생 여성의 삶과 일상 속 성차별 문제를 고발한 소설"
    }
  ],
  "흑산": [
    {
      "location": "대한민국 전라남도 신안군 흑산도",
      "event": "조선 후기 천주교 박해와 유배된 지식인의 삶을 그린 역사소설."
    }
  ],
  "남한산성": [
    {
      "location": "남한산성",
      "event": "병자호란 당시 조선 인조가 항전과 항복 사이에서 고뇌한 역사를 배경으로 함"
    }
  ],
  "이순신의 7년": [
    {
      "location": "대한민국 전라남도 해역, 경상남도 해역",
      "event": "임진왜란 7년간 이순신 장군과 백성들의 전쟁과 삶을 재조명."
    }
  ],
  "경성 탐정록": [
    {
      "location": "일제강점기 경성(서울)",
      "event": "1930년대 경성을 배경으로 좀비와 미스터리를 결합한 탐정 활극."
    }
  ],
  "타인의 집": [
    {
      "location": "대한민국 서울",
      "event": "전셋집 불법 월세 셰어하우스를 무대로 인간관계와 삶의 조건을 묘사."
    }
  ],
  "공터에서": [
    {
      "location": "대한민국 서울",
      "event": "1945년 해방 이후 한국전쟁, 5.18, 6월 항쟁 등 현대사 속 민초들의 삶을 다룸"
    }
  ],
  "망원동 브라더스": [
    {
      "location": "대한민국 서울시 마포구 망원동",
      "event": "옥탑방에서 동거하는 네 남자의 세대별 인생 고군분투기를 그린 작품."
    }
  ],
  "메밀꽃 필 무렵": [
    {
      "location": "대한민국 강원도 봉평",
      "event": "봉평 장터와 메밀꽃밭을 배경으로 장돌뱅이의 삶과 사랑을 서정적으로 묘사."
    }
  ],
  "천변풍경": [
    {
      "location": "서울특별시 종로구·중구 청계천 일대",
      "event": "1930년대 서울 청계천변 서민들의 생활상과 도시 풍속을 파노라마처럼 묘사."
    }
  ],
  "서울은 천국이다": [
    {
      "location": "서울특별시 도심",
      "event": "1960년대 서울을 배경으로 이주·도시화 속 인물들의 삶과 열망을 그린 소설.",
      "note": "정확한 동네 스펙은 판본/해석에 따라 달라질 수 있음."
    }
  ],
  "화분": [
    {
      "location": "서울특별시 종로구 일대",
      "event": "도시 생활 속 인간관계와 욕망을 은유적으로 드러내는 단편.",
      "note": "작품·판본별 공간 표기 상이, 종로 일대 배경으로 알려짐(확인 필요)."
    }
  ],
  "장마": [
    {
      "location": "서울특별시 변두리",
      "event": "도시 빈민가를 배경으로 한 가족과 시대의 균열을 그린 작품.",
      "note": "작가·작품에 따라 다른 '장마'가 존재함. 본 매핑은 도심 변두리 해석 기반."
    }
  ],
  "강화도": [
    {
      "location": "인천광역시 강화군",
      "event": "섬과 갯벌, 역사 유적을 배경으로 주민들의 삶과 풍경을 담은 서사."
    }
  ],
  "바다와 나비": [
    {
      "location": "인천광역시 중구·동구 항구 일대",
      "event": "항구 도시의 정서와 이동/이별의 이미지를 중심으로 한 작품(시·산문 포함)."
    }
  ],
  "부산 사람": [
    {
      "location": "부산광역시 중구·서구 원도심",
      "event": "원도심 골목과 시장을 배경으로 한 부산 토박이들의 삶과 정서."
    }
  ],
  "모래톱 이야기": [
    {
      "location": "부산광역시 영도구",
      "event": "개발과 수탈에 맞서는 섬마을 사람들의 연대와 저항을 그린 작품."
    }
  ],
  "무정": [
    {
      "location": "대구광역시 중구·북구 일대",
      "event": "개화기 지식인의 사랑과 계몽을 다룬 근대 장편. 대구·서울을 오가며 전개.",
      "note": "주요 무대는 서울이나 대구 장면이 반복 등장."
    }
  ],
  "달구벌": [
    {
      "location": "대구광역시",
      "event": "대구(달구벌)의 역사·도시 변천과 사람들의 이야기를 소재로 함.",
      "note": "동명 르포/소설·에세이 등 다수. 소설적 재현 기준으로 매핑."
    }
  ],
  "5월의 사람들": [
    {
      "location": "광주광역시 동구·북구 일대",
      "event": "광주 5·18 민주화운동을 배경으로 사람들의 선택과 연대를 다룸.",
      "note": "동명 논픽션/소설 유형 다양. 소설적 읽기를 기준으로 매핑."
    }
  ],
  "광주 이야기": [
    {
      "location": "광주광역시",
      "event": "광주 지역 인물과 사건을 통해 도시의 정체성과 기억을 환기."
    }
  ],
  "대전 블루스": [
    {
      "location": "대전광역시 동구 대전역·원도심",
      "event": "대전역과 원도심을 무대로 청춘의 상실·기억·귀환을 그린 서사."
    }
  ],
  "대전 스토리": [
    {
      "location": "대전광역시 중구·서구",
      "event": "도시 재개발과 개인사의 교차 속에서 대전의 현재를 포착."
    }
  ],
  "반구대": [
    {
      "location": "울산광역시 울주군 언양읍(반구대 암각화)",
      "event": "고대와 현재가 맞닿는 공간에서 인간·문명에 대한 성찰을 그린 장편."
    }
  ],
  "세종을 걷다": [
    {
      "location": "세종특별자치시 정부세종청사·호수공원 일대",
      "event": "신도시의 형성과 일상의 리듬을 산책담으로 엮은 서사.",
      "note": "르포/에세이 성격 강함. 소설적 매핑으로 활용."
    }
  ],
  "조치원 해문이": [
    {
      "location": "세종특별자치시 조치원읍",
      "event": "충청도 사투리와 농촌 마을의 인물을 통해 지역 정서를 드러내는 작품."
    }
  ],
  "수원 화성": [
    {
      "location": "경기도 수원시 팔달구·장안구(화성 일대)",
      "event": "정조의 화성 축성과 도성의 삶을 모티프로 한 이야기."
    }
  ],
  "양평": [
    {
      "location": "경기도 양평군",
      "event": "북한강·두물머리와 산촌 마을을 배경으로 관계의 치유와 회복을 다룸."
    }
  ],
  "동백꽃": [
    {
      "location": "강원특별자치도 춘천시 신북읍 실레마을",
      "event": "시골 총각과 처녀의 애정담을 해학적으로 그린 단편."
    }
  ],
  "설악산": [
    {
      "location": "강원특별자치도 속초시·양양군 설악산 국립공원",
      "event": "설악의 산세·사찰·계곡을 배경으로 인간과 자연을 성찰."
    }
  ],
  "정선 아리랑": [
    {
      "location": "강원특별자치도 정선군",
      "event": "정선 탄광·장터와 아리랑 서사를 통해 지역 정체성을 재현."
    }
  ],
  "태백산": [
    {
      "location": "강원특별자치도 태백시·영월군(태백산)",
      "event": "산촌 공동체와 광산 노동의 기억을 산악 공간에 중첩."
    }
  ],
  "제천 의병": [
    {
      "location": "충청북도 제천시",
      "event": "한말 제천 의병 항쟁의 공간과 인물들을 따라가는 역사 서사."
    }
  ],
  "청주 사람들": [
    {
      "location": "충청북도 청주시",
      "event": "도시 확장과 생활 변화를 겪는 청주 시민들의 일상을 포착."
    }
  ],
  "논산 이야기": [
    {
      "location": "충청남도 논산시",
      "event": "훈련소·강경읍·농촌 마을을 배경으로 한 지역 르포성 서사."
    }
  ],
  "아산의 봄": [
    {
      "location": "충청남도 아산시 곡교천 일대",
      "event": "하천·들녘 풍경 속에서 지역의 사계와 인간사를 엮는다."
    }
  ],
  "변산": [
    {
      "location": "전북특별자치도 부안군 변산반도국립공원",
      "event": "모항·채석강·내소사 등 변산의 지형·사찰을 무대로 한 이야기."
    }
  ],
  "완주 사람들": [
    {
      "location": "전북특별자치도 완주군",
      "event": "농촌 혁신·로컬 문화 속 주민들의 삶과 일터를 그린 작품."
    }
  ],
  "순천만": [
    {
      "location": "전라남도 순천시 순천만 습지",
      "event": "갈대밭·갯벌 생태와 도시 주변 마을의 일상을 그린 지역 서사."
    }
  ],
  "경주 남산": [
    {
      "location": "경상북도 경주시 남산",
      "event": "신라 불상·마애불과 고적을 배경으로 역사와 현재의 대화를 구성."
    }
  ],
  "안동의 밤": [
    {
      "location": "경상북도 안동시(하회·월영교 일대)",
      "event": "하회마을·낙동강 주변의 밤 풍경 속 인물의 내면 여정."
    }
  ],
  "포항 바다": [
    {
      "location": "경상북도 포항시 남구·북구 해안",
      "event": "제철소·항만·어촌의 공존 속에서 노동·도시의 리듬을 포착."
    }
  ],
  "창원 사람들": [
    {
      "location": "경상남도 창원시 성산구 창원국가산단",
      "event": "공단 도시의 노동·이주·정착의 기억을 인물 군상으로 서술."
    }
  ],
  "제주 이야기": [
    {
      "location": "제주특별자치도 전역(제주시·서귀포시)",
      "event": "섬 고유의 신화·민속·마을 공동체를 토대로 한 옴니버스 형식."
    }
  ],
  "한라산": [
    {
      "location": "제주특별자치도 한라산 국립공원",
      "event": "한라산 화산지형과 4·3의 기억을 잇는 역사·서정 서사."
    }
  ],
  "삼국유사": [
  {
    "location": "경상도(인각사 등)",
    "event": "일연이 1280년대 불교 설화·신화 중심으로 집필한 사서"
  }
  ],
  "징비록": [
    {
      "location": "조선 경상도 안동",
      "event": "유성룡이 임진왜란 체험을 바탕으로 반성·경계 기록"
    }
  ],
  "난중일기": [
    {
      "location": "전라·경상 남해 일대",
      "event": "이순신이 전쟁 중 남긴 일기 기록"
    }
  ],
  "춘향전": [
    {
      "location": "전라북도 남원",
      "event": "이몽룡과 성춘향의 사랑, 암행어사의 변학도 응징"
    }
  ],
  "별주부전": [
    {
      "location": "남해 바다",
      "event": "용왕 병을 고치기 위한 토끼 간 모티프의 판소리계 소설"
    }
  ],
  "장화홍련전": [
    {
      "location": "경기도 광주·양주",
      "event": "계모의 모함으로 죽은 자매의 원혼과 진실 규명 설화"
    }
  ],
  "박씨전": [
    {
      "location": "조선 한성·남한산성",
      "event": "병자호란 배경 여성 영웅 박씨 부인의 구국담"
    }
  ],
  "금오신화": [
    {
      "location": "경주 금오산 일대",
      "event": "김시습이 쓴 우리 고전 최초의 소설집, 기이담 중심"
    }
  ],
  "사씨남정기": [
    {
      "location": "조선 한성",
      "event": "가부장제·첩 질서 비판의 가정소설, 정경부인 사씨의 복권"
    }
  ],
  "임꺽정": [
    {
      "location": "경기도",
      "event": "연산군 시기 의적 임꺽정의 활약을 그린 소설"
    }
  ],
  "상록수": [
    {
      "location": "경기도 안산",
      "event": "농촌계몽과 청년 지식인의 사랑·헌신"
    }
  ],
  "탁류": [
    {
      "location": "전북 군산",
      "event": "일제강점기 군산 포구의 빈곤·부패·여성의 수난"
    }
  ],
  "광장": [
    {
      "location": "서울",
      "event": "분단 현실 속 선택의 비극, 남북 체제 비판"
    }
  ],
  "오발탄": [
    {
      "location": "서울 청계천 일대",
      "event": "6·25 전후의 가난과 좌절을 그린 리얼리즘 소설"
    }
  ],
  "삼포가는 길": [
    {
      "location": "강원도 삼포",
      "event": "도시 변두리 노동자들의 유랑과 상실"
    }
  ],
  "관촌수필": [
    {
      "location": "전라북도 임실 관촌",
      "event": "농촌의 변화와 유년의 추억을 그린 수필 연작"
    }
  ],
  "감자": [
    {
      "location": "서울 변두리",
      "event": "가난에 내몰린 복녀의 비극을 그린 자연주의 단편"
    }
  ],
  "운수 좋은 날": [
    {
      "location": "서울 종로·청계천",
      "event": "일용인부 김첨지의 비극적 하루"
    }
  ],
  "빈처": [
    {
      "location": "서울",
      "event": "나도향의 신문명·신가정 담론을 담은 단편"
    }
  ],
  "님의 침묵": [
    {
      "location": "서대문형무소 등",
      "event": "한용운의 독립과 사랑의 상징시집"
    }
  ],
  "하늘과 바람과 별과 시": [
    {
      "location": "서울 종로·서대문",
      "event": "윤동주의 일제강점기 청년 서정과 저항의 시집"
    }
  ],
  "성호사설": [
    {
      "location": "경기도 안산",
      "event": "이익이 백과적으로 집필한 실학 사설집"
    }
  ],
  "한중록": [
    {
      "location": "수원 화성",
      "event": "혜경궁 홍씨가 기록한 사도세자·정조 시대 궁중회고록"
    }
  ],
  "유배지에서 보낸 편지": [
    {
      "location": "전라도 강진·해남",
      "event": "정약용이 유배지에서 가족·제자에게 보낸 편지 모음"
    }
  ],
  "표해록": [
    {
      "location": "제주",
      "event": "장한철의 표류 체험 기록"
    }
  ],
  "용재총화": [
    {
      "location": "한성",
      "event": "성현이 세태·문화를 기록한 필기문학"
    }
  ],
  "지봉유설": [
    {
      "location": "한성",
      "event": "이수광의 백과전서적 문헌"
    }
  ],
  "소나기": [
    {
      "location": "경기도",
      "event": "소년·소녀의 첫사랑과 비극"
    }
  ],
  "객지": [
    {
      "location": "부산·인천 등 도시 변두리",
      "event": "1970년대 노동운동·하층민 삶을 그린 리얼리즘 소설"
    }
  ],
  "서울 1964년 겨울": [
    {
      "location": "서울 광화문·다방",
      "event": "도시 소외와 실존적 공허를 그린 단편"
    }
  ],
  "사슴": [
    {
      "location": "서울",
      "event": "백석의 모더니즘 시집, 방언과 이미지의 결합"
    }
  ],
  "진달래꽃": [
    {
      "location": "서울",
      "event": "김소월의 민요적 정한과 이별의 정서를 담은 시집"
    }
  ],
  "오감도": [
    {
      "location": "서울",
      "event": "이상(李箱)의 실험적 모더니즘 연작시"
    }
  ],
  "청록집": [
    {
      "location": "경기도·강원 산천",
      "event": "박목월·박두진·조지훈의 자연 서정 공동시집"
    }
  ],



  "파친코": [
    {
      "location": "부산과 일본 오사카·요코하마",
      "event": "재일 조선인 가문의 이주와 차별, 생존의 역사를 4대에 걸쳐 그린다."
    }
  ],
  "채식주의자": [
    {
      "location": "대한민국 서울",
      "event": "평범했던 여성이 고기를 거부하며 가족과 사회의 폭력에 맞선다."
    }
  ],
  "아몬드": [
    {
      "location": "대한민국 서울",
      "event": "감정을 느끼기 어려운 소년이 상처와 우정을 통해 성장한다."
    }
  ],
  "불편한 편의점": [
    {
      "location": "대한민국 서울의 동네 편의점",
      "event": "밤마다 일하는 의문의 아르바이트생이 손님과 이웃들의 삶을 다정하게 바꾼다."
    }
  ],
  "뿌리깊은 나무": [
    {
      "location": "조선 한성(서울) 궁궐과 집현전",
      "event": "세종 때 연쇄 살인을 둘러싸고 훈민정음 창제의 비밀과 권력 암투가 교차한다."
    }
  ],
  "바리데기": [
    {
      "location": "평양과 중국·서울",
      "event": "탈북 소녀 바리데기가 고난의 여정을 거쳐 새로운 삶을 찾아가는 이야기."
    }
  ],
  "원미동 사람들": [
    {
      "location": "경기도 부천시 원미동",
      "event": "1980년대 소도시 변두리 마을 주민들의 소소한 일상을 통해 한국 사회를 비춘 소설."
    }
  ],
  "청구회 추억": [
    {
      "location": "서울",
      "event": "이광수가 유학 시절 청년 지식인들의 이상과 우정을 회상한 소설."
    }
  ],
  "삼대": [
    {
      "location": "서울 종로·한성",
      "event": "조선 말기부터 일제강점기를 거치는 세 세대 가족의 가치관 충돌과 변화를 그린 소설."
    }
  ],

    "소설가 구보씨의 일일": [
    { "location": "서울특별시 종로구 일대(당시 경성)", "event": "하루 산책 속에 근대 도시의 공기와 지식인의 내면을 그려낸 모더니즘 소설." }
  ],
   "날개": [
    { "location": "서울특별시(당시 경성)", "event": "무력한 화자가 자아해체를 겪는 실험적 서사로 근대의 균열을 보여준다." }
  ],
  "만세전": [
    { "location": "인천광역시 중구(제물포)·서울특별시·일본 도쿄도", "event": "귀국길의 지식인이 식민지 현실에 대한 환멸과 자각을 독백적으로 토로한다." }
  ],
  "허생전": [
    { "location": "서울특별시·인천광역시 강화군", "event": "몰락 양반 허생의 기상천외한 실험을 통해 조선 사회의 병폐를 풍자한다." }
  ],
  "홍길동전": [
    { "location": "서울특별시·가상공간 ‘율도국’", "event": "서얼 차별을 딛고 의적이 된 길동이 불의한 질서를 뒤엎는 모험담." }
  ],
  "구운몽": [
    { "location": "서울특별시(옛 한양)·경기도 양주시 및 꿈속 타지", "event": "한 꿈속의 영화가 덧없음을 깨닫는 승려 성진/양소유의 일대기." }
  ],
  "손님": [
    { "location": "북한 황해남도 신천군 및 남한 월남 지역(회상/증언)", "event": "한국전쟁기 종교·이념 폭력이 낳은 민간인 학살의 진실을 공동체의 기억으로 복원한다." }
  ],
  "김약국의 딸들": [
    { "location": "경상남도 통영시", "event": "약국 집안 네 딸의 삶을 통해 바닷도시의 정한과 근대의 격랑을 담는다." }
  ],
  "바람의 화원": [
    { "location": "서울특별시 종로구(창덕궁·창경궁 등 궁궐/화원 일대)", "event": "신윤복과 김홍도를 모티프로, 궁중 화단의 비밀과 스승·제자의 예술을 그린다." }
  ],
  "수난이대": [
    { "location": "전라남도 해안 어촌(신안군·고흥군 일대, 작중 불특정)", "event": "전쟁 상흔을 지닌 부자(父子)가 바다에서 노동하며 삶을 이어가는 이야기." }
  ],
  "혈의 누": [
    { "location": "인천광역시 중구(제물포)·일본 도쿄도", "event": "낡은 질서의 폭력과 인신매매를 겪은 여성의 각성과 귀환을 그린 근대 계몽소설.", "note": "판본에 따라 세부 전개와 지명 표기가 상이함." }
  ],
    "장길산": [
    {
      "location": "전북특별자치도 고창군·정읍시, 전라남도 해남군 등",
      "event": "조선 후기 몰락한 민중이 의적 장길산을 중심으로 탐관오리와 맞서는 대하 역사소설."
    }
  ],
  "오래된 정원": [
    {
      "location": "전라남도 화순군·서울특별시",
      "event": "1980년대 운동권 남성과 화가 여성이 시대의 탄압 속에서 사랑과 기다림을 이어간다."
    }
  ],
  "무소유": [
    {
      "location": "전라남도 순천시 송광사 일대",
      "event": "법정 스님이 소유를 비우는 삶의 태도와 사색을 담은 산문집."
    }
  ],
  "봉순이 언니": [
    {
      "location": "서울특별시 종로구·중구 청계천 판자촌 일대",
      "event": "공장과 빈민가를 무대로 여성 노동자와 화자의 연대와 상처를 그린 성장기."
    }
  ],
  "고래": [
    {
      "location": "경상북도 포항시·울산광역시 인접 가상 항구도시",
      "event": "변방의 여인이 산업화의 소용돌이 속에서 욕망과 신화를 일구는 마술적 리얼리즘 장편."
    }
  ],
  "우리들의 행복한 시간": [
    {
      "location": "서울특별시, 경상북도 청송군 교정시설",
      "event": "죽음을 앞둔 사형수와 삶을 포기한 여성이 서로의 고통을 보듬으며 희망을 찾아간다."
    }
  ],
  "국화꽃 향기": [
    {
      "location": "서울특별시",
      "event": "연인의 병과 이별을 통해 사랑의 지속과 기억을 다룬 서정적 이야기."
    }
  ],
  "마당을 나온 암탉": [
    {
      "location": "경기도 양평군 들녘(해석)",
      "event": "양계장을 탈출한 암탉 잎새가 낯선 자연에서 모성으로 거듭나는 여정."
    }
  ],
  "풀꽃도 꽃이다": [
    {
      "location": "서울특별시 강남구·서초구 고등학교(가상)",
      "event": "입시 경쟁 속 교사·학부모·학생이 상처를 마주하고 교육의 본질을 모색한다."
    }
  ],
  "카인의 후예": [
    {
      "location": "평안북도 농촌(현 북한 지역)",
      "event": "해방 직후 북녘 마을에서 토지개혁과 종교·이념 갈등이 빚는 비극을 그린다."
    }
  ],
  "장군의 아들": [
    {
      "location": "서울특별시 종로구·중구(일제강점기)",
      "event": "김두한이 종로 거리에서 성장하며 폭력과 의협, 식민지 현실과 맞선다."
    }
  ],
  "영원한 제국": [
    {
      "location": "서울특별시 종로구 경복궁·창덕궁 일대",
      "event": "정조 독살 의혹을 둘러싼 궁중 정치와 지식인의 진실 추적을 그린 역사 미스터리."
    }
  ],
  "엄마의 말뚝": [
    {
      "location": "서울특별시 영등포구·구로구 일대",
      "event": "도시 변두리 이주 정착 속에서 모녀가 겪는 생존, 기억, 애증을 그린 자전적 서사."
    }
  ],
  "무녀도": [
    {
      "location": "경상북도 경주시 인근 가상 마을",
      "event": "무속과 기독교의 충돌 속에서 한 가족이 해체되는 비극을 통해 전통과 근대의 균열을 드러낸다."
    }
  ],
  "갯마을": [
    {
      "location": "울산광역시 울주군 서생면 어촌(해석)",
      "event": "동해안 어촌 여성의 사랑과 상실, 바다의 냉혹함과 연대의 온기를 그린다."
    }
  ],
  "태평천하": [
    {
      "location": "전북특별자치도 군산시",
      "event": "식민지 현실을 외면하는 지주 가문을 풍자하며 몰락과 허위를 드러낸 채만식의 풍자소설."
    }
  ],
  "덕혜옹주": [
    {
      "location": "서울특별시 종로구 경복궁·일본 도쿄도·시마네현 등",
      "event": "대한제국 마지막 황녀의 유년과 일본 거처, 귀국과 말년을 따라가는 역사소설."
    }
  ],
  "은교": [
    {
      "location": "경기도 성남시 일대(가상 주소 설정)",
      "event": "노시인과 제자, 소녀 사이의 욕망과 예술, 시간의 잔혹함을 응시하는 서사."
    }
  ],
  "난설헌": [
    {
      "location": "강원특별자치도 강릉시",
      "event": "시인 허난설헌의 생애를 바탕으로 여성·재능·운명에 대해 재해석한 역사소설."
    }
  ],
    "도가니": [
    {
      "location": "광주광역시 북구",
      "event": "실화를 바탕으로 특수학교에서 벌어진 성폭력을 고발하고, 시민의 연대로 진실을 밝히는 과정을 그린다."
    }
  ],
  "빛의 제국": [
    {
      "location": "서울특별시",
      "event": "서울에 잠입한 북한 공작원이 본국 소환 24시간을 앞두고 마지막 선택을 고민한다."
    }
  ],
  "설계자들": [
    {
      "location": "서울특별시 종로구·중구 일대",
      "event": "비밀 암살조직에 소속된 킬러가 조직의 음모와 자신의 과거를 추적한다."
    }
  ],
  "피프티 피플": [
    {
      "location": "서울특별시(대학병원·응급실, 가상)",
      "event": "한 대형병원을 중심으로 50명의 삶이 사고·치유·연대의 서사로 얽힌다."
    }
  ],
  "보건교사 안은영": [
    {
      "location": "서울특별시 강남구 사립고등학교(가상)",
      "event": "괴상한 ‘젤리’를 보는 보건교사가 학교 곳곳의 미스터리를 해결한다."
    }
  ],
  "경애의 마음": [
    {
      "location": "인천광역시·서울특별시",
      "event": "정리해고와 상실을 겪은 두 직장인이 서로를 통해 회복의 언어를 배워간다."
    }
  ],
  "우아한 거짓말": [
    {
      "location": "서울특별시(신도시 아파트 단지, 가상)",
      "event": "중학생의 갑작스런 죽음 뒤 남겨진 가족이 학교 폭력의 진실을 마주한다."
    }
  ],
  "화산도": [
    {
      "location": "제주특별자치도 전역(제주시·서귀포시)",
      "event": "제주 4·3의 상처가 세대를 건너 이어지며 섬사람들의 삶과 유배의 기억을 비춘다."
    }
  ],
  "고향": [
    {
      "location": "충청남도 아산시·당진시 농촌(해석)",
      "event": "해방 직후 농촌에서 소작제 붕괴와 계급 갈등이 폭발하는 과정을 그린다."
    }
  ],
  "눈길": [
    {
      "location": "전라남도 해남군 산촌(해석)",
      "event": "가난한 산골의 모자가 눈길을 내려오며 삶의 고단함과 애증을 성찰한다."
    }
  ],
  "사람의 아들": [
    {
      "location": "서울특별시",
      "event": "한 신학자의 의문사 이후 진리와 신을 둘러싼 탐문이 이어지는 철학소설."
    }
  ],
  "서동요": [
    {
      "location": "충청남도 부여군·전북특별자치도 익산시",
      "event": "서동과 선화공주의 설화를 토대로 백제·신라의 권력 암투와 사랑을 그린다."
    }
  ],
  "완전한 행복": [
    {
      "location": "서울특별시·경기도(용인·성남 일대, 해석)",
      "event": "완벽을 강요하는 남자의 집착 아래 숨 막히는 관계의 심리가 드러난다."
    }
  ],
  "바깥은 여름": [
    {
      "location": "인천광역시·서울특별시 등 도시(단편집, 배경 다양)",
      "event": "도시의 일상에서 벌어진 사고 이후 가족과 개인이 상실을 견디는 모습을 그린다."
    }
  ],
  "왕을 찾아서": [
    {
      "location": "경상북도 문경시·예천군에서 전국 각지",
      "event": "정체불명의 ‘왕’을 찾아 떠난 사내가 유랑길에서 만난 민초들의 초상을 그린다."
    }
  ],
  "투명인간": [
    {
      "location": "서울특별시 도봉구·노원구 등 강북 변두리(해석)",
      "event": "평생 성실히 살아온 남자가 사회의 시선에서 ‘투명’해지는 과정을 그린다."
    }
  ],
  "미생": [
    {
      "location": "서울특별시 중구·종로구 오피스가",
      "event": "바둑을 꿈꾸다 상경한 신입사원이 대기업에서 생존과 성장을 모색한다."
    }
  ],
  "무진기행": [
    {
      "location": "전라남도 보성군·순천시·벌교읍(모티프)",
      "event": "안개 자욱한 고향 ‘무진’으로 내려온 화자가 서울과 지방 사이에서 느끼는 공허와 욕망을 성찰한다."
    }
  ],
  "서편제": [
    {
      "location": "전라남도 해남군·진도군",
      "event": "남도 들녘과 산길을 떠돌며 소리를 닦는 판소리 명창 부녀의 예술과 상흔을 그린다."
    }
  ],
  "두근두근 내 인생": [
    {
      "location": "서울특별시",
      "event": "유전자 질환을 지닌 소년과 젊은 부모가 일상의 사랑과 선택을 통해 삶의 의미를 찾아간다."
    }
  ],
  "위저드 베이커리": [
    {
      "location": "서울특별시",
      "event": "가출한 소년이 신비한 빵집에서 ‘마법과 빵’으로 치유와 연대를 경험하는 청소년 판타지."
    }
  ],
  "성균관 유생들의 나날": [
    {
      "location": "서울특별시 종로구(성균관·창덕궁 일대)",
      "event": "정조 시대 성균관을 무대로 금녀의 금기를 넘어 유생들과 사건을 헤쳐 나가는 청춘 사극."
    }
  ],
  "당신들의 천국": [
    {
      "location": "전라남도 고흥군 도양읍 소록도",
      "event": "소록도 한센병원 개혁을 둘러싸고 이상과 현실, 권력과 돌봄의 윤리를 치열하게 묻는다."
    }
  ]
}